{
  "PageId": "21401790-9b01-47b3-a955-b7e19ed0ebb2",
  "Title": "Workshop mit Bauhütte 4.0 und Tegel Projekt GmbH",
  "Authors": [
    {
      "id": "94c8e3de-62f8-41ab-83d1-dc738d41a45e",
      "name": "Daniel Dieren",
      "color": "green"
    },
    {
      "id": "gt`}",
      "name": "Julia Dorn",
      "color": "default"
    }
  ],
  "Category": "Events",
  "Icon": null,
  "Cover": {
    "Type": "file",
    "Url": "https://prod-files-secure.s3.us-west-2.amazonaws.com/03753020-4f11-4175-8523-330762c8abd9/eb7aeef2-ab07-4888-85a9-17d96da0cee1/workshop-bauhuette40-tegel-projekt_cover.jpg?X-Amz-Algorithm=AWS4-HMAC-SHA256&X-Amz-Content-Sha256=UNSIGNED-PAYLOAD&X-Amz-Credential=ASIAZI2LB4663JWQV63K%2F20251023%2Fus-west-2%2Fs3%2Faws4_request&X-Amz-Date=20251023T172612Z&X-Amz-Expires=3600&X-Amz-Security-Token=IQoJb3JpZ2luX2VjEJH%2F%2F%2F%2F%2F%2F%2F%2F%2F%2FwEaCXVzLXdlc3QtMiJHMEUCIQDIOTO125huZc5rphJp2D9KaXCux4Lp5McnCKiFvGocvQIgMp2QuKwMWcd1uUNXZ4e6i4d0%2F4dneuXXShBtsduqoloq%2FwMIShAAGgw2Mzc0MjMxODM4MDUiDOqfoiwhETahmubrpSrcA%2BcuL%2BwbxWmXXAzTR58S3lmmFqaCDkTwLbYjnFTUjduO6NJKyTTQiMVCQN1Qakn98SSd1bmnk829VbPvM4VbFKLmagHxUW8e%2BpCRzC%2FP0mIo2P9fxtf2Q3VhDBNu3FCa%2BdnztSQlE05uNSfsUmUzPOcEstjxaPTE3jD5CgWP%2FXSyBcP%2FfnxZVS2%2FDfJfguKYvhbFnxUEqQMPQOGf3uUOtRW1lOnMLkqmoYYqB3CSF6daFQeV%2Fx%2B3e1fLS3QT7OXIUeVHGYC9EHfZ8QSIv81r5OynaDWooJUJkGtEiKR55JiAJiG1%2F5tE8v%2FLjUzbLacV2GyMj6U%2FGYtej9oR7MiqC8rnfWTO7AzPRPc9on6ET3S0hzlIe9AgPYrmjaBeeJlntyTNrawbuHV0Qjf22p%2FPdY3bVoN%2BAPfFIb3lNObtZD6MqLI56HRKU%2F0Z0goJgN4FEreJopV5R0Yk4fwLEOsypZYlaKy26C8t6Rykp9lqBdOn%2BfIwwmJ7xpVREiGm1oW16XVMO18VBT90%2BT6ee8Cegdmft4IWvgYqEHNd22pNCMFq6j4bw1zZ3H2jYwt3JX2c4N8ywIyPwmDjfN99AWupWKB3PMpUvqpADD3gzzGO8DP184tMERD0cbI0VTpNMNC%2B6ccGOqUBGgWeXfiNLY%2FdDCniTrVzObzDl4fE%2Faa8IF1Bl20d1%2Bs5XT0kqZTRSWRULoOzcGuKqrcUyeAWaevvKX4hlNSKtrxQpku2bcjlz6%2BfyFE9%2B3FNwesDohnl0w8duE4tb%2BGS5UXrjZnZV9BMwG3BpqEC%2BT2xjUt2u8wBgiELgKznc2w1HChCSBdJ1Hg6vIKLEbiNnIeL6LBB1H0nRnuYzegdgj9h8HGv&X-Amz-Signature=003b747c9c9591229741a2cda909e687d2e0886b92d3f9963a3c0f8996e184ef&X-Amz-SignedHeaders=host&x-amz-checksum-mode=ENABLED&x-id=GetObject"
  },
  "CoverAlt": "Workshop participants brainstorming ideas",
  "Slug": "workshop-bauhuette40-tegel-projekt",
  "PublishDate": "2024-02-22",
  "Tags": [
    {
      "id": "fd49549e-a8cb-4310-bdc4-c783c3bd93ef",
      "name": "Ökobilanzierung",
      "color": "red"
    },
    {
      "id": "b6127d5c-2d61-4c4a-8bee-fdad8130b1a7",
      "name": "Zirkularität",
      "color": "default"
    },
    {
      "id": "9184f45b-71c1-4ab7-8948-05cf3382e607",
      "name": "Holzbau",
      "color": "green"
    }
  ],
  "Description": "Daniel Dieren leitete den Workshop der Bauhütte 4.0 zur Bewertung der Nachhaltigkeit von Bauprojekten.",
  "coverAsset": "workshop-bauhuette40-tegel-projekt_cover.jpg",
  "blockAssets": [
    "daniel-dieren_bewertung-der-nachhaltigkeit-von-konstruktionen-im-holzbau.jpg",
    "prof-raoul-bunschoten-und-daniel-dieren-bei-dem-workshop.jpg"
  ],
  "blocks": [
    {
      "Id": "2087e842-f5f6-49de-a52f-1108f213cedc",
      "Type": "paragraph",
      "HasChildren": false,
      "ParentId": "21401790-9b01-47b3-a955-b7e19ed0ebb2",
      "Paragraph": {
        "RichTexts": [
          {
            "Annotation": {
              "Bold": false,
              "Italic": false,
              "Strikethrough": false,
              "Underline": false,
              "Code": false,
              "Color": "default"
            },
            "PlainText": "Klimaschutz und Nachhaltigkeit können nur in  Verbindung mit der Bezahlbarkeit von Bauen und Wohnen sozialverträglich und wirksam zukunftsfähig verfolgt werden. Um den Einsatz nachhaltiger Bauweisen  zu fördern, gewinnen Methoden zur Bewertung der Gebäudekonstruktion zunehmend an Bedeutung.",
            "Href": null,
            "Text": {
              "Content": "Klimaschutz und Nachhaltigkeit können nur in  Verbindung mit der Bezahlbarkeit von Bauen und Wohnen sozialverträglich und wirksam zukunftsfähig verfolgt werden. Um den Einsatz nachhaltiger Bauweisen  zu fördern, gewinnen Methoden zur Bewertung der Gebäudekonstruktion zunehmend an Bedeutung."
            }
          }
        ],
        "Color": "default"
      }
    },
    {
      "Id": "0be30656-434d-4bf0-a02a-0fbf760ddc91",
      "Type": "paragraph",
      "HasChildren": false,
      "ParentId": "21401790-9b01-47b3-a955-b7e19ed0ebb2",
      "Paragraph": {
        "RichTexts": [
          {
            "Annotation": {
              "Bold": false,
              "Italic": false,
              "Strikethrough": false,
              "Underline": false,
              "Code": false,
              "Color": "default"
            },
            "PlainText": "Daniel Dieren von BuildSystems leitete die Werkstatt der ",
            "Href": null,
            "Text": {
              "Content": "Daniel Dieren von BuildSystems leitete die Werkstatt der "
            }
          },
          {
            "Annotation": {
              "Bold": false,
              "Italic": false,
              "Strikethrough": false,
              "Underline": false,
              "Code": false,
              "Color": "default"
            },
            "PlainText": "Bauhütte 4.0",
            "Href": "https://www.bauhuette40.com/?lang=de",
            "Text": {
              "Content": "Bauhütte 4.0",
              "Link": {
                "Url": "https://www.bauhuette40.com/?lang=de"
              }
            }
          },
          {
            "Annotation": {
              "Bold": false,
              "Italic": false,
              "Strikethrough": false,
              "Underline": false,
              "Code": false,
              "Color": "default"
            },
            "PlainText": ", Tunca Beril Basaran unterstütze bei der Vorbereitung und Durchführung. Begleitet wurde der Workshop durch Prof. Raoul Bunschoten und Simon Kimmel von der Bauhütte 4.0. In der Diskussion mit Expert:innen wurden alternative Bewertungsmechanismen untersucht, die die Verwendung von nachwachsenden Rohstoffen priorisieren.  Die wachsenden Anforderungen der EU-Taxonomie, der EU-Gebäuderichtlinie und der Nachhaltigkeitsberichterstattung (",
            "Href": null,
            "Text": {
              "Content": ", Tunca Beril Basaran unterstütze bei der Vorbereitung und Durchführung. Begleitet wurde der Workshop durch Prof. Raoul Bunschoten und Simon Kimmel von der Bauhütte 4.0. In der Diskussion mit Expert:innen wurden alternative Bewertungsmechanismen untersucht, die die Verwendung von nachwachsenden Rohstoffen priorisieren.  Die wachsenden Anforderungen der EU-Taxonomie, der EU-Gebäuderichtlinie und der Nachhaltigkeitsberichterstattung ("
            }
          },
          {
            "Annotation": {
              "Bold": false,
              "Italic": false,
              "Strikethrough": false,
              "Underline": false,
              "Code": false,
              "Color": "default"
            },
            "PlainText": "LEVELS",
            "Href": "https://environment.ec.europa.eu/topics/circular-economy/levels_en",
            "Text": {
              "Content": "LEVELS",
              "Link": {
                "Url": "https://environment.ec.europa.eu/topics/circular-economy/levels_en"
              }
            }
          },
          {
            "Annotation": {
              "Bold": false,
              "Italic": false,
              "Strikethrough": false,
              "Underline": false,
              "Code": false,
              "Color": "default"
            },
            "PlainText": "), sowie auf nationaler Ebene durch die Weiterentwicklung der GEG und BEG, führen zwangsläufig zu einer frühzeitigen Bewertung oder Bilanzierung geplanter Immobilien. Neue Bewertungsansätze zur Nachhaltigkeit von Baukonstruktionen müssen sowohl den ökologischen Anforderungen zur Dekarbonisierung des Gebäudesektors gerecht werden, als auch die wirtschaftliche Umsetzbarkeit sicherstellen.  Im Rahmen des Workshops wurden mögliche Ansätze für die nächste Iteration von Bewertungssysteme identifiziert. ",
            "Href": null,
            "Text": {
              "Content": "), sowie auf nationaler Ebene durch die Weiterentwicklung der GEG und BEG, führen zwangsläufig zu einer frühzeitigen Bewertung oder Bilanzierung geplanter Immobilien. Neue Bewertungsansätze zur Nachhaltigkeit von Baukonstruktionen müssen sowohl den ökologischen Anforderungen zur Dekarbonisierung des Gebäudesektors gerecht werden, als auch die wirtschaftliche Umsetzbarkeit sicherstellen.  Im Rahmen des Workshops wurden mögliche Ansätze für die nächste Iteration von Bewertungssysteme identifiziert. "
            }
          }
        ],
        "Color": "default"
      }
    },
    {
      "Id": "4d422f01-6e7d-4121-8d09-04f27dc49e21",
      "Type": "image",
      "HasChildren": false,
      "ParentId": "21401790-9b01-47b3-a955-b7e19ed0ebb2",
      "Image": {
        "Caption": [
          {
            "Annotation": {
              "Bold": false,
              "Italic": false,
              "Strikethrough": false,
              "Underline": false,
              "Code": false,
              "Color": "default"
            },
            "PlainText": "Daniel Dieren: Bewertung der Nachhaltigkeit von Konstruktionen im Holzbau\nDaniel Dieren: Bewertung der Nachhaltigkeit von Konstruktionen im Holzbau",
            "Href": null,
            "Text": {
              "Content": "Daniel Dieren: Bewertung der Nachhaltigkeit von Konstruktionen im Holzbau\nDaniel Dieren: Bewertung der Nachhaltigkeit von Konstruktionen im Holzbau"
            }
          }
        ],
        "Type": "file",
        "File": {
          "Type": "file",
          "Url": "https://prod-files-secure.s3.us-west-2.amazonaws.com/03753020-4f11-4175-8523-330762c8abd9/a1a60328-985e-448a-9e84-ca8ae27a11dc/daniel-dieren_bewertung-der-nachhaltigkeit-von-konstruktionen-im-holzbau.jpg?X-Amz-Algorithm=AWS4-HMAC-SHA256&X-Amz-Content-Sha256=UNSIGNED-PAYLOAD&X-Amz-Credential=ASIAZI2LB466UYWFJEWE%2F20251023%2Fus-west-2%2Fs3%2Faws4_request&X-Amz-Date=20251023T172614Z&X-Amz-Expires=3600&X-Amz-Security-Token=IQoJb3JpZ2luX2VjEJH%2F%2F%2F%2F%2F%2F%2F%2F%2F%2FwEaCXVzLXdlc3QtMiJHMEUCIQC5P%2FJikR8qEMkxf4D8VA0K1d2CsZCTcEVeoPTt4YQpXwIgbONtZibwaGCGZlq5gexClpKlZI0nGWgFs3Zc3eOjVQQq%2FwMIShAAGgw2Mzc0MjMxODM4MDUiDHRqusY0X0rxmG0t9SrcAzoqpK9B0VmlNaWhbeVAu0zmuMQNAoTt2oWzJaeHSqm3CPQNALBKLC5Vja4YMOeSQNWx%2BlMAH%2BtRXFgiu%2BHvgNUMmCFWD7nh54oIt%2B%2BdgeSc5qOoEBVrO%2BM%2BdAc3gWBADqSUC3XXWlfa4x5odSRZ8B23oiZPrlLXrp5cQa7z7nWXlgKqFSdymb2QDa1bp61pSKXV15X5W4kIT7dvpMhbmTFjcLK22PPQ%2Fpl7riWpUiOmozpDJAmzsPZP5J1KkRRU1sKVhL%2FZkTRUHE3odiRjrpPOTD5ZbF1urzPskb7AHKtNgSPjtOa1qTgPaizCNwaIpf3AV1wawCbaGfXTtyiQhQq3KLi0U%2FcDQi2xN46K%2FrUFLjwh9F6VIeh9NNHfN6FR5Mw%2F%2FXCKVV8DgKkmgiWqm42HZoJHOKGBoPDuU4k4jJ0xSu7tLagWCMUL75QLqoKzw8HuuvyVhEGzJbvfgYZT%2BCQEdjYLUS2sYg7uXaz9vwdjR2a6bX4HPPHV%2BEn1r4B0Yjx4dmiTN5aXxlym8k6G6jWc2KdXSA%2B9X5mO8slNh3mqpvPGfoA86IC5Z6KKBxECrkK%2BC62IuvG2j%2BDYYtXMmk04%2Bw79p4AsIIPKEhkurhWexnrcwxPEbgrjl5lSMJa%2F6ccGOqUBQmHDXcW5eFxkpeERgdx7koHX%2BMVK0XNlcQ80bU6VL9wIj0fUHkpqTmXaxEclFNIq1A%2BtKJyS45xjyiZT%2F97lHfyO164HlhMc4mVm%2F1uqD6xIIlcIic7jd66KJvrUGQyZYQJN8zmYgrv7RlgrO6Nf%2FAOHLJhB%2FjbEdClAY1Q93VrCUcdOI1rluHJQ9TLvfXic1fEDGwOI6lxotx5LvR2bhBTAwDcf&X-Amz-Signature=257b2de81414999fb9d18764f0c0b5bd51d48a40c17bf3abd7716cacb5963c23&X-Amz-SignedHeaders=host&x-amz-checksum-mode=ENABLED&x-id=GetObject",
          "ExpiryTime": "2025-10-23T18:26:14.749Z"
        }
      }
    },
    {
      "Id": "2d5b5e35-8591-4e0a-92c9-61be9110b8b4",
      "Type": "heading_2",
      "HasChildren": false,
      "ParentId": "21401790-9b01-47b3-a955-b7e19ed0ebb2",
      "Heading2": {
        "RichTexts": [
          {
            "Annotation": {
              "Bold": false,
              "Italic": false,
              "Strikethrough": false,
              "Underline": false,
              "Code": false,
              "Color": "default"
            },
            "PlainText": "Hier sind einige wichtige Erkenntnisse aus unserem Workshop",
            "Href": null,
            "Text": {
              "Content": "Hier sind einige wichtige Erkenntnisse aus unserem Workshop"
            }
          }
        ],
        "Color": "default",
        "IsToggleable": false
      }
    },
    {
      "Id": "dd8839c8-4527-447c-9923-0f2b1147ec4f",
      "Type": "paragraph",
      "HasChildren": false,
      "ParentId": "21401790-9b01-47b3-a955-b7e19ed0ebb2",
      "Paragraph": {
        "RichTexts": [
          {
            "Annotation": {
              "Bold": false,
              "Italic": false,
              "Strikethrough": false,
              "Underline": false,
              "Code": false,
              "Color": "default"
            },
            "PlainText": "Kontrastierende Ansätze: Der Ansatz eines Bewertungssystems zur Förderung des Holzbaus durch den Nachweis der verbauten Holzmasse wird in Frage gestellt. Dadurch werden massive Bauteile aufgrund ihrer höheren Masse an Holzwerkstoffen gegenüber Tafelbauten bevorzugt, was häufig mit erhöhten Kosten einher geht. Das übergeordnete Ziel bleibt die Dekarbonisierung des Gebäudesektors, unabhängig von der gewählten Bauweise. Daher sollte sich der Fokus von der Bewertung des Kohlenstoffspeichers und des NawaRo-Anteils auf eine konstruktionsunabhängige Bewertung anhand des Treibhauspotenzials verschieben.",
            "Href": null,
            "Text": {
              "Content": "Kontrastierende Ansätze: Der Ansatz eines Bewertungssystems zur Förderung des Holzbaus durch den Nachweis der verbauten Holzmasse wird in Frage gestellt. Dadurch werden massive Bauteile aufgrund ihrer höheren Masse an Holzwerkstoffen gegenüber Tafelbauten bevorzugt, was häufig mit erhöhten Kosten einher geht. Das übergeordnete Ziel bleibt die Dekarbonisierung des Gebäudesektors, unabhängig von der gewählten Bauweise. Daher sollte sich der Fokus von der Bewertung des Kohlenstoffspeichers und des NawaRo-Anteils auf eine konstruktionsunabhängige Bewertung anhand des Treibhauspotenzials verschieben."
            }
          }
        ],
        "Color": "default"
      }
    },
    {
      "Id": "9b34a493-f5e8-4353-a900-11b428c868ca",
      "Type": "paragraph",
      "HasChildren": false,
      "ParentId": "21401790-9b01-47b3-a955-b7e19ed0ebb2",
      "Paragraph": {
        "RichTexts": [
          {
            "Annotation": {
              "Bold": false,
              "Italic": false,
              "Strikethrough": false,
              "Underline": false,
              "Code": false,
              "Color": "default"
            },
            "PlainText": "Mapping Parameter: Die Definition von Indikatoren ermöglicht es, die Nachhaltigkeit von Konstruktionen messbar zu machen. Benchmarks dienen dazu, sinnvolle Grenz- und Zielwerte festzulegen. Ökobilanzierungen werden in der Praxis häufig im direkten Bauteilvergleich angewandt. Die Verwendung von Bauteilkatalogen für Standardkonstruktionen kann für eine erste Bewertung im Rahmen einer Konzeptvergabe hilfreich sein. Idealerweise sollte die Klassifizierung von Bauteilen in Zukunft nicht anhand der Bauweise, sondern auf Basis von bauteilspezifischen Benchmarks erfolgen. Für die Akzeptanz von Bewertungssystemen bleibt die Balance zwischen Anwendbarkeit und Genauigkeit maßgebend.",
            "Href": null,
            "Text": {
              "Content": "Mapping Parameter: Die Definition von Indikatoren ermöglicht es, die Nachhaltigkeit von Konstruktionen messbar zu machen. Benchmarks dienen dazu, sinnvolle Grenz- und Zielwerte festzulegen. Ökobilanzierungen werden in der Praxis häufig im direkten Bauteilvergleich angewandt. Die Verwendung von Bauteilkatalogen für Standardkonstruktionen kann für eine erste Bewertung im Rahmen einer Konzeptvergabe hilfreich sein. Idealerweise sollte die Klassifizierung von Bauteilen in Zukunft nicht anhand der Bauweise, sondern auf Basis von bauteilspezifischen Benchmarks erfolgen. Für die Akzeptanz von Bewertungssystemen bleibt die Balance zwischen Anwendbarkeit und Genauigkeit maßgebend."
            }
          }
        ],
        "Color": "default"
      }
    },
    {
      "Id": "0ba2cee2-0164-4338-95f7-9a60e4735fc4",
      "Type": "paragraph",
      "HasChildren": false,
      "ParentId": "21401790-9b01-47b3-a955-b7e19ed0ebb2",
      "Paragraph": {
        "RichTexts": [
          {
            "Annotation": {
              "Bold": false,
              "Italic": false,
              "Strikethrough": false,
              "Underline": false,
              "Code": false,
              "Color": "default"
            },
            "PlainText": "Zirkularität: Indikatoren für zirkuläres Bauen gewinnen an Bedeutung, hingegen verlieren solche für nachwachsende Rohstoffe an Relevanz. Das Treibhauspotenzial bleibt eine universelle Kenngröße. Während jedoch der Mangel an Daten und rechtliche Unsicherheiten von zirkulären Bauprodukten Herausforderungen darstellen, können Referenz-Bauteilkataloge und Datenbanken wie Madaster ebenso wie die frühzeitige Einbeziehung von Fachplanern helfen. Entsprechende Anreize in Bewertungssystemen, zum Beispiel durch das Abfragen von Rückbaukonzepten, sollten frühzeitig berücksichtigt werden.",
            "Href": null,
            "Text": {
              "Content": "Zirkularität: Indikatoren für zirkuläres Bauen gewinnen an Bedeutung, hingegen verlieren solche für nachwachsende Rohstoffe an Relevanz. Das Treibhauspotenzial bleibt eine universelle Kenngröße. Während jedoch der Mangel an Daten und rechtliche Unsicherheiten von zirkulären Bauprodukten Herausforderungen darstellen, können Referenz-Bauteilkataloge und Datenbanken wie Madaster ebenso wie die frühzeitige Einbeziehung von Fachplanern helfen. Entsprechende Anreize in Bewertungssystemen, zum Beispiel durch das Abfragen von Rückbaukonzepten, sollten frühzeitig berücksichtigt werden."
            }
          }
        ],
        "Color": "default"
      }
    },
    {
      "Id": "1257699c-3d59-429a-8431-e147d1340c75",
      "Type": "paragraph",
      "HasChildren": false,
      "ParentId": "21401790-9b01-47b3-a955-b7e19ed0ebb2",
      "Paragraph": {
        "RichTexts": [
          {
            "Annotation": {
              "Bold": false,
              "Italic": false,
              "Strikethrough": false,
              "Underline": false,
              "Code": false,
              "Color": "default"
            },
            "PlainText": "Im Austausch mit den Teilnehmenden von CHORA conscious city, Brandschutz Akademie Berlin, Technische Universität Berlin, Scharabi Architekten, drmm studio, Knippers Helbig Ingenieure, Tegel Projekt GmbH, Timbatec Holzbauingenieure, Fraunhofer- Institut PK, Niil Architekten, PSD Bank, Berliner Sparkassen, Sauerbruch Hutton, Playze Timber GmbH und Deimel Oelschläger Architekten ergab sich eine rege Diskussion und wichtige Insights. ",
            "Href": null,
            "Text": {
              "Content": "Im Austausch mit den Teilnehmenden von CHORA conscious city, Brandschutz Akademie Berlin, Technische Universität Berlin, Scharabi Architekten, drmm studio, Knippers Helbig Ingenieure, Tegel Projekt GmbH, Timbatec Holzbauingenieure, Fraunhofer- Institut PK, Niil Architekten, PSD Bank, Berliner Sparkassen, Sauerbruch Hutton, Playze Timber GmbH und Deimel Oelschläger Architekten ergab sich eine rege Diskussion und wichtige Insights. "
            }
          }
        ],
        "Color": "default"
      }
    },
    {
      "Id": "5c7c0a73-d152-4227-acfa-49e08c042363",
      "Type": "paragraph",
      "HasChildren": false,
      "ParentId": "21401790-9b01-47b3-a955-b7e19ed0ebb2",
      "Paragraph": {
        "RichTexts": [
          {
            "Annotation": {
              "Bold": false,
              "Italic": false,
              "Strikethrough": false,
              "Underline": false,
              "Code": false,
              "Color": "default"
            },
            "PlainText": "Die Ergebnisse werden nun bei der Prozessgestaltung zur Vergabe des ",
            "Href": null,
            "Text": {
              "Content": "Die Ergebnisse werden nun bei der Prozessgestaltung zur Vergabe des "
            }
          },
          {
            "Annotation": {
              "Bold": false,
              "Italic": false,
              "Strikethrough": false,
              "Underline": false,
              "Code": false,
              "Color": "default"
            },
            "PlainText": "Schumacher Quartiers",
            "Href": "https://schumacher-quartier.de/",
            "Text": {
              "Content": "Schumacher Quartiers",
              "Link": {
                "Url": "https://schumacher-quartier.de/"
              }
            }
          },
          {
            "Annotation": {
              "Bold": false,
              "Italic": false,
              "Strikethrough": false,
              "Underline": false,
              "Code": false,
              "Color": "default"
            },
            "PlainText": " der ",
            "Href": null,
            "Text": {
              "Content": " der "
            }
          },
          {
            "Annotation": {
              "Bold": false,
              "Italic": false,
              "Strikethrough": false,
              "Underline": false,
              "Code": false,
              "Color": "default"
            },
            "PlainText": "Tegel Projekt GmbH",
            "Href": "https://tegelprojekt.de/",
            "Text": {
              "Content": "Tegel Projekt GmbH",
              "Link": {
                "Url": "https://tegelprojekt.de/"
              }
            }
          },
          {
            "Annotation": {
              "Bold": false,
              "Italic": false,
              "Strikethrough": false,
              "Underline": false,
              "Code": false,
              "Color": "default"
            },
            "PlainText": " verwendet. ",
            "Href": null,
            "Text": {
              "Content": " verwendet. "
            }
          }
        ],
        "Color": "default"
      }
    },
    {
      "Id": "21125287-ac18-4856-ab04-6f03dbd318e4",
      "Type": "column_list",
      "HasChildren": true,
      "ParentId": "21401790-9b01-47b3-a955-b7e19ed0ebb2",
      "ColumnList": {
        "Columns": [
          {
            "Id": "01639fc3-30b2-4cb7-844d-c608f5c8b857",
            "Type": "column",
            "HasChildren": true,
            "Children": [
              {
                "Id": "253b7ae1-b616-48ac-89ff-a01bf52fbad7",
                "Type": "image",
                "HasChildren": false,
                "Image": {
                  "Caption": [
                    {
                      "Annotation": {
                        "Bold": false,
                        "Italic": false,
                        "Strikethrough": false,
                        "Underline": false,
                        "Code": false,
                        "Color": "default"
                      },
                      "PlainText": "Prof. Raoul Bunschoten und Daniel Dieren bei dem Workshop\nProf. Raoul Bunschoten und Daniel Dieren bei dem Workshop",
                      "Href": null,
                      "Text": {
                        "Content": "Prof. Raoul Bunschoten und Daniel Dieren bei dem Workshop\nProf. Raoul Bunschoten und Daniel Dieren bei dem Workshop"
                      }
                    }
                  ],
                  "Type": "file",
                  "File": {
                    "Type": "file",
                    "Url": "https://prod-files-secure.s3.us-west-2.amazonaws.com/03753020-4f11-4175-8523-330762c8abd9/1f438af5-ecaa-4bce-ad16-1f322caac252/prof-raoul-bunschoten-und-daniel-dieren-bei-dem-workshop.jpeg?X-Amz-Algorithm=AWS4-HMAC-SHA256&X-Amz-Content-Sha256=UNSIGNED-PAYLOAD&X-Amz-Credential=ASIAZI2LB46676XOKY7Q%2F20251023%2Fus-west-2%2Fs3%2Faws4_request&X-Amz-Date=20251023T172615Z&X-Amz-Expires=3600&X-Amz-Security-Token=IQoJb3JpZ2luX2VjEJH%2F%2F%2F%2F%2F%2F%2F%2F%2F%2FwEaCXVzLXdlc3QtMiJHMEUCIQDE7iInjJb5LkuQ9de6fa6cQMfsFy1ScGCtbcNZhizjmgIgRV%2Fh1X1Bct8ci4tMI9065vJ50GEOHCCjl%2BPcOty%2FFjoq%2FwMIShAAGgw2Mzc0MjMxODM4MDUiDJ2DYkiJ2Gk46XXm%2FircA6zAqwHgSE8Tp2lxiBwaj2x%2BFYEOX8yjqyZzDnxgpE8BrnH2a%2BdZh%2Ftl%2FKtzG2KveTV9vZK1qWAW9S4M9O085u3dV9WlwWIrO9fwPogf31sM%2FmVI2Oe%2BJCxZnA277%2Bje%2FGx3%2Bs81ADvOni0M0aJksCX%2FocxRPTY4dx3%2B9JmHN8ufqvjd6PiN4f7iwTe5sMWj1Qmdx8CB%2FZlcr%2BT%2BL2DU9oecbdl5%2F%2BDpQcdXhriW0eFE62UCGxJW3diPkP9TYvzmT5wCJNuDw9az9Stjne23Qb0LZCEIRfVKZhrkC%2BRqVXpIsD5mtEijvXeIHjoRbdio%2FEYzBYo%2ByatSKDGTvYVLdjwmsdIjZ8qqyCmL8KffNtaBPsHIAjcBddDCWRT4BgQ4LzdnYH6cnMYmfeoLBX6V6yNueR4J5FwXArk9Y2ECBFRvYE%2BY4WevRIAJvbN3hM3y2DLdsuDzd79mwgNSttv39nmCyatU%2BXUbcslfN0uAHFBIpzVPgPH%2FEIa%2FVi7R%2BJj%2BUBZLYwc85OTldPd%2BFsLZEkPvHV1uiPWXK5d6WAWfXIRLJ38JOUOd67umLPpp4sxctRUzgtoG3L3gJvSFNW4Ol8fm5LD%2FR%2FH8Zh8yw%2BM4wSzY1p3z9y6kd0qetpoLMMC%2F6ccGOqUBsKDu2c4U9%2FRtadFgaVHQWMH7E0F3GKDyOB0XpbbrlwVhpUe4HrKqwTENxEs7ujJizDJec1ftr%2BSz05qgsi61LdrWFzVWSvvjiFxOell%2FgYQnmW6x4LsETi5czPVqFM5mLGE%2BhtkihWAqvQfVcgU2rFhnrcep2%2BK%2F1OVr9UFlQ10lQJCU%2FJypMQam6iNJn6KQ4faGfJSggjIpWR7NnYDRzO9bsoAE&X-Amz-Signature=de772b956c9d1f34c54f8f57158b05ebf29723cc511d34332d6eab7632360392&X-Amz-SignedHeaders=host&x-amz-checksum-mode=ENABLED&x-id=GetObject",
                    "ExpiryTime": "2025-10-23T18:26:15.479Z"
                  }
                }
              }
            ]
          },
          {
            "Id": "e3335adb-993a-42e2-aa6e-79a50651f77a",
            "Type": "column",
            "HasChildren": true,
            "Children": [
              {
                "Id": "877f9006-a150-48cb-b848-1907940c9ab0",
                "Type": "paragraph",
                "HasChildren": false,
                "Paragraph": {
                  "RichTexts": [],
                  "Color": "default"
                }
              }
            ]
          }
        ]
      }
    },
    {
      "Id": "41864a51-c05f-419c-b60a-cc7b99934a3f",
      "Type": "paragraph",
      "HasChildren": false,
      "ParentId": "21401790-9b01-47b3-a955-b7e19ed0ebb2",
      "Paragraph": {
        "RichTexts": [],
        "Color": "default"
      }
    },
    {
      "Id": "83c7e27c-4e41-46e3-a3b7-2d92319349b2",
      "Type": "paragraph",
      "HasChildren": false,
      "ParentId": "21401790-9b01-47b3-a955-b7e19ed0ebb2",
      "Paragraph": {
        "RichTexts": [
          {
            "Annotation": {
              "Bold": false,
              "Italic": false,
              "Strikethrough": false,
              "Underline": false,
              "Code": false,
              "Color": "default"
            },
            "PlainText": "©️ ",
            "Href": null,
            "Text": {
              "Content": "©️ "
            }
          },
          {
            "Annotation": {
              "Bold": false,
              "Italic": false,
              "Strikethrough": false,
              "Underline": false,
              "Code": false,
              "Color": "default"
            },
            "PlainText": "Cover & Images: Raquel Gómez Delgado",
            "Href": null,
            "Text": {
              "Content": "Cover & Images: Raquel Gómez Delgado"
            }
          }
        ],
        "Color": "default"
      }
    }
  ]
}