{
  "PageId": "01a1e2d2-3f1f-4aae-b756-6e6bbde8bef3",
  "Title": "Lehrauftrag an der TU München - Professur für “Architecture and Design”",
  "Authors": [
    {
      "id": "52892f86-d7a8-43c8-a3e2-5c40a49a6f18",
      "name": "Martin Bittmann",
      "color": "brown"
    },
    {
      "id": "gt`}",
      "name": "Julia Dorn",
      "color": "default"
    }
  ],
  "Category": "Teaching",
  "Icon": {
    "Type": "external",
    "Url": "https://www.notion.so/icons/feed_gray.svg"
  },
  "Cover": {
    "Type": "file",
    "Url": "https://prod-files-secure.s3.us-west-2.amazonaws.com/03753020-4f11-4175-8523-330762c8abd9/9a710eaf-0d1e-4035-87de-8ea0d2ee54ff/lehrauftrag-tum_workshop.png?X-Amz-Algorithm=AWS4-HMAC-SHA256&X-Amz-Content-Sha256=UNSIGNED-PAYLOAD&X-Amz-Credential=ASIAZI2LB4663JWQV63K%2F20251023%2Fus-west-2%2Fs3%2Faws4_request&X-Amz-Date=20251023T172612Z&X-Amz-Expires=3600&X-Amz-Security-Token=IQoJb3JpZ2luX2VjEJH%2F%2F%2F%2F%2F%2F%2F%2F%2F%2FwEaCXVzLXdlc3QtMiJHMEUCIQDIOTO125huZc5rphJp2D9KaXCux4Lp5McnCKiFvGocvQIgMp2QuKwMWcd1uUNXZ4e6i4d0%2F4dneuXXShBtsduqoloq%2FwMIShAAGgw2Mzc0MjMxODM4MDUiDOqfoiwhETahmubrpSrcA%2BcuL%2BwbxWmXXAzTR58S3lmmFqaCDkTwLbYjnFTUjduO6NJKyTTQiMVCQN1Qakn98SSd1bmnk829VbPvM4VbFKLmagHxUW8e%2BpCRzC%2FP0mIo2P9fxtf2Q3VhDBNu3FCa%2BdnztSQlE05uNSfsUmUzPOcEstjxaPTE3jD5CgWP%2FXSyBcP%2FfnxZVS2%2FDfJfguKYvhbFnxUEqQMPQOGf3uUOtRW1lOnMLkqmoYYqB3CSF6daFQeV%2Fx%2B3e1fLS3QT7OXIUeVHGYC9EHfZ8QSIv81r5OynaDWooJUJkGtEiKR55JiAJiG1%2F5tE8v%2FLjUzbLacV2GyMj6U%2FGYtej9oR7MiqC8rnfWTO7AzPRPc9on6ET3S0hzlIe9AgPYrmjaBeeJlntyTNrawbuHV0Qjf22p%2FPdY3bVoN%2BAPfFIb3lNObtZD6MqLI56HRKU%2F0Z0goJgN4FEreJopV5R0Yk4fwLEOsypZYlaKy26C8t6Rykp9lqBdOn%2BfIwwmJ7xpVREiGm1oW16XVMO18VBT90%2BT6ee8Cegdmft4IWvgYqEHNd22pNCMFq6j4bw1zZ3H2jYwt3JX2c4N8ywIyPwmDjfN99AWupWKB3PMpUvqpADD3gzzGO8DP184tMERD0cbI0VTpNMNC%2B6ccGOqUBGgWeXfiNLY%2FdDCniTrVzObzDl4fE%2Faa8IF1Bl20d1%2Bs5XT0kqZTRSWRULoOzcGuKqrcUyeAWaevvKX4hlNSKtrxQpku2bcjlz6%2BfyFE9%2B3FNwesDohnl0w8duE4tb%2BGS5UXrjZnZV9BMwG3BpqEC%2BT2xjUt2u8wBgiELgKznc2w1HChCSBdJ1Hg6vIKLEbiNnIeL6LBB1H0nRnuYzegdgj9h8HGv&X-Amz-Signature=97ee7e86ad361db4d15ad353c2b13a85cd8d73e6f1532f878629135168594efb&X-Amz-SignedHeaders=host&x-amz-checksum-mode=ENABLED&x-id=GetObject"
  },
  "CoverAlt": "Plakat Wood Oberpfalz Abschlusspräsentation",
  "Slug": "lehrauftrag-tum",
  "PublishDate": "2023-09-22",
  "Tags": [
    {
      "id": "9184f45b-71c1-4ab7-8948-05cf3382e607",
      "name": "Holzbau",
      "color": "green"
    },
    {
      "id": "e779dcf8-c54a-4fca-ba1c-21595d3d70c1",
      "name": "Bauwende",
      "color": "pink"
    },
    {
      "id": "3cb599cd-3066-4de1-abce-1a4752f6d114",
      "name": "Dekarbonisierung",
      "color": "gray"
    },
    {
      "id": "9cb996a6-a071-40fc-b58e-a4c3f52e72f0",
      "name": "Digitalisierung",
      "color": "yellow"
    },
    {
      "id": "b6127d5c-2d61-4c4a-8bee-fdad8130b1a7",
      "name": "Zirkularität",
      "color": "default"
    },
    {
      "id": "fd49549e-a8cb-4310-bdc4-c783c3bd93ef",
      "name": "Ökobilanzierung",
      "color": "red"
    }
  ],
  "Description": "BuildSystems begleitete Studierende der TU München bei der Analyse und Adaption regionaler Holz-Wertschöpfungsketten.",
  "coverAsset": "lehrauftrag-tum_workshop.jpg",
  "blockAssets": [
    "lehrauftrag-tum-concluding_event.jpg",
    "eaf216ff-c704-401d-8c71-36445d6f58fc.jpg",
    "lehrauftrag-tum_zukunftsvision.jpg",
    "lehrauftrag-tum_material_experiments.jpg",
    "lehrauftrag-tum_film_still.jpg",
    "lehrauftrag-tum_concluding_event_2.jpg",
    "lehrauftrag-tum_concluding_event_3.jpg"
  ],
  "blocks": [
    {
      "Id": "98dfff0f-c828-4b99-996c-f59a7aeb42b5",
      "Type": "heading_2",
      "HasChildren": false,
      "ParentId": "01a1e2d2-3f1f-4aae-b756-6e6bbde8bef3",
      "Heading2": {
        "RichTexts": [
          {
            "Annotation": {
              "Bold": false,
              "Italic": false,
              "Strikethrough": false,
              "Underline": false,
              "Code": false,
              "Color": "default"
            },
            "PlainText": "Wood Oberpfalz - Regionale Wertschöpfungsketten",
            "Href": null,
            "Text": {
              "Content": "Wood Oberpfalz - Regionale Wertschöpfungsketten"
            }
          }
        ],
        "Color": "default",
        "IsToggleable": false
      }
    },
    {
      "Id": "ee0b01fc-8b92-4f6b-acb3-ff8d6280d62c",
      "Type": "paragraph",
      "HasChildren": false,
      "ParentId": "01a1e2d2-3f1f-4aae-b756-6e6bbde8bef3",
      "Paragraph": {
        "RichTexts": [
          {
            "Annotation": {
              "Bold": false,
              "Italic": false,
              "Strikethrough": false,
              "Underline": false,
              "Code": false,
              "Color": "default"
            },
            "PlainText": "Julia Dorn und Martin Bittmann von BuildSystems waren im Wintersemester 2022/23 Teil des Expertennetzwerks für das Master-Studio von Professor Niklas Fanelsa und seinem Team an der Professur \"Architecture und Design\" an der Technischen Universität München. In Zusammenarbeit mit dem Lehrstuhl, dem Expertennetzwerk aus BuildSystems, Studio Sarmite und Material Cultures sowie der Genossenschaft Holzversorgung Oberpfalz e.G. formulierten die Studierenden neue Potenziale einer regionalen Holzkreislaufwirtschaft in der Oberpfalz. ",
            "Href": null,
            "Text": {
              "Content": "Julia Dorn und Martin Bittmann von BuildSystems waren im Wintersemester 2022/23 Teil des Expertennetzwerks für das Master-Studio von Professor Niklas Fanelsa und seinem Team an der Professur \"Architecture und Design\" an der Technischen Universität München. In Zusammenarbeit mit dem Lehrstuhl, dem Expertennetzwerk aus BuildSystems, Studio Sarmite und Material Cultures sowie der Genossenschaft Holzversorgung Oberpfalz e.G. formulierten die Studierenden neue Potenziale einer regionalen Holzkreislaufwirtschaft in der Oberpfalz. "
            }
          }
        ],
        "Color": "default"
      }
    },
    {
      "Id": "08dc653e-02b3-455e-b320-69555f378623",
      "Type": "paragraph",
      "HasChildren": false,
      "ParentId": "01a1e2d2-3f1f-4aae-b756-6e6bbde8bef3",
      "Paragraph": {
        "RichTexts": [
          {
            "Annotation": {
              "Bold": false,
              "Italic": false,
              "Strikethrough": false,
              "Underline": false,
              "Code": false,
              "Color": "default"
            },
            "PlainText": "Im Zuge des \"Living Lab\" wurde zunächst mit Feldforschung und Mapping und Design-Thinking-Methoden gearbeitet, um ein ganzheitliches Verständnis von Architektur und deren Einfluss auf regionale Wertschöpfung sowie lokale Ökosysteme zu fördern. Das Team von BuildSystems brachte seine Expertise aus früheren Forschungsarbeiten ein, um die Studierenden dabei zu unterstützen, Erkenntnisse aus der Systemanalyse in materielle und digitale Prototypen zu übertragen. Im Verlauf des Semesters wurden Wissensformate erarbeitet, Zukunftsvszenarien in Form von KI-generierten Videos entwickelt und Materialexperimente sowie Möbel aus Holz realisiert. Alle Projekte verfolgten dabei allesamt das Ziel, die Wertschöpfung abseits der Industrie möglichst regional zu halten sowie kreislauffähige und emissionsreduzierte Potenziale zu eröffnen. Die Prototypen wurden im Pavillon 333 in München ausgestellt und von einer Diskussion mit Vertretern der Forstwirtschaft in der Oberpfalz begleitet.",
            "Href": null,
            "Text": {
              "Content": "Im Zuge des \"Living Lab\" wurde zunächst mit Feldforschung und Mapping und Design-Thinking-Methoden gearbeitet, um ein ganzheitliches Verständnis von Architektur und deren Einfluss auf regionale Wertschöpfung sowie lokale Ökosysteme zu fördern. Das Team von BuildSystems brachte seine Expertise aus früheren Forschungsarbeiten ein, um die Studierenden dabei zu unterstützen, Erkenntnisse aus der Systemanalyse in materielle und digitale Prototypen zu übertragen. Im Verlauf des Semesters wurden Wissensformate erarbeitet, Zukunftsvszenarien in Form von KI-generierten Videos entwickelt und Materialexperimente sowie Möbel aus Holz realisiert. Alle Projekte verfolgten dabei allesamt das Ziel, die Wertschöpfung abseits der Industrie möglichst regional zu halten sowie kreislauffähige und emissionsreduzierte Potenziale zu eröffnen. Die Prototypen wurden im Pavillon 333 in München ausgestellt und von einer Diskussion mit Vertretern der Forstwirtschaft in der Oberpfalz begleitet."
            }
          }
        ],
        "Color": "default"
      }
    },
    {
      "Id": "75728930-67a6-4bb1-830b-f696cc6cc1f5",
      "Type": "paragraph",
      "HasChildren": false,
      "ParentId": "01a1e2d2-3f1f-4aae-b756-6e6bbde8bef3",
      "Paragraph": {
        "RichTexts": [],
        "Color": "default"
      }
    },
    {
      "Id": "70136bee-802b-4b34-b551-c197280b2eef",
      "Type": "image",
      "HasChildren": false,
      "ParentId": "01a1e2d2-3f1f-4aae-b756-6e6bbde8bef3",
      "Image": {
        "Caption": [
          {
            "Annotation": {
              "Bold": false,
              "Italic": false,
              "Strikethrough": false,
              "Underline": false,
              "Code": false,
              "Color": "default"
            },
            "PlainText": "Diskussion während der Abschlussveranstaltung",
            "Href": null,
            "Text": {
              "Content": "Diskussion während der Abschlussveranstaltung"
            }
          }
        ],
        "Type": "file",
        "File": {
          "Type": "file",
          "Url": "https://prod-files-secure.s3.us-west-2.amazonaws.com/03753020-4f11-4175-8523-330762c8abd9/ee962b88-0b32-4b4a-92bf-7ce7eb9af2f8/lehrauftrag-tum-concluding_event.png?X-Amz-Algorithm=AWS4-HMAC-SHA256&X-Amz-Content-Sha256=UNSIGNED-PAYLOAD&X-Amz-Credential=ASIAZI2LB466TECN5POE%2F20251023%2Fus-west-2%2Fs3%2Faws4_request&X-Amz-Date=20251023T172615Z&X-Amz-Expires=3600&X-Amz-Security-Token=IQoJb3JpZ2luX2VjEJH%2F%2F%2F%2F%2F%2F%2F%2F%2F%2FwEaCXVzLXdlc3QtMiJIMEYCIQDuoccapCmG0hMzX%2FKsj9xxPp8Oc4%2FtlY%2B0soMHngz6ogIhAKZIMr69ipp7RMcMwECKSTpCd5UUmL3E7OX%2Bfj%2B2g1oCKv8DCEoQABoMNjM3NDIzMTgzODA1IgxCGKZFX3OO%2BCwZ4cQq3ANAMFc8d5rkgpEqK5B5XrG28ipbX2Ftg62kdWQqvau4n%2BR%2FA0iey8zZYUDtvKFeWvnR9OXewZPReYWHUCcd%2FnMz5Aslinf%2BRMHeUr7H1lMub%2FwCywNAjZLXzSkKNF%2BwIVQuvUGce3v%2FJ4uwtPIXa1qDJVIpul0WmDQbg71sTMEDxgty2jHx4DEfNdc%2FsxdbfiYZ2aphex9ZZ%2B8MlQOre8UpivOAkNowyOMVs2ca9TPfvl8z3JlH9NkFBUDNB7SU%2FRLCSmEo2ZmI%2B21cX7iBhWPDc%2BOE%2FlaYX76LxE9o1cEnQOnWR4v5ONF3E9d4%2BYpgxUAXYRyfNZK3UPJDLLbTa8X1hB8OkvwJV7moFlw9RU2sE1v7Q780yO5u2njJa3eD42qcSrKSZexEOHc11XO5%2FTQ76KBzEJvq9SW6pfthT5z1BzBhF%2BwIAv4myM9IvCYtDvCzpmpEKVNDKpOSF5BWZwnsvp48wwwcCsZ5x4trtSfS9mwYQrC1u08lEx%2FTG0YxtyiUvXNVgv9okncm2%2Fqv7rWZHN7BZKGo9LquRzEl5XGOnZgQC%2B7hzjuXAbitJJ1mFb0KbG%2BOYXLtmPChhhThCcBARaA0gIsn8vfzPU%2BRLkLeQNcypuJUGNP%2BW59BVzCNv%2BnHBjqkAeKxmHXhi59aocGjU8ER3GBFhYDNbOhQs%2BOkQS8e83lEW%2FHvdPFBIEaIDPlysq%2Bk5pDGbYpsIYB0%2Be9zJw9bDdXRx%2F1PQQZ3vbMf6tdNTONYJN0YFSn5H%2FHmUnHguYUnzGlRpv0rQPSEE%2F%2BLju8BT%2FnvlR3x%2BaKh4w2AWc%2B9tAeN%2Bl7vxDxq7GsOx5F9KJYxroUdEc5mXqrUBK7DLCoQdHCTWVGf&X-Amz-Signature=4b1d6cf4d08fc608d36db8fb71a71c5091b60e306ac0e5f7c249ec1d36360a88&X-Amz-SignedHeaders=host&x-amz-checksum-mode=ENABLED&x-id=GetObject",
          "ExpiryTime": "2025-10-23T18:26:15.468Z"
        }
      }
    },
    {
      "Id": "683734d7-5501-4d9f-b9a5-123fe6db8c42",
      "Type": "column_list",
      "HasChildren": true,
      "ParentId": "01a1e2d2-3f1f-4aae-b756-6e6bbde8bef3",
      "ColumnList": {
        "Columns": [
          {
            "Id": "e764795b-b2f0-4e41-ae3a-cc358ac4c0d4",
            "Type": "column",
            "HasChildren": true,
            "Children": [
              {
                "Id": "3a120808-d4dc-4991-8787-b266faf761ed",
                "Type": "image",
                "HasChildren": false,
                "Image": {
                  "Caption": [
                    {
                      "Annotation": {
                        "Bold": false,
                        "Italic": false,
                        "Strikethrough": false,
                        "Underline": false,
                        "Code": false,
                        "Color": "default"
                      },
                      "PlainText": "How-to-circulate Cards von Zeynep Argat und Helena Dzerve",
                      "Href": null,
                      "Text": {
                        "Content": "How-to-circulate Cards von Zeynep Argat und Helena Dzerve"
                      }
                    }
                  ],
                  "Type": "file",
                  "File": {
                    "Type": "file",
                    "Url": "https://prod-files-secure.s3.us-west-2.amazonaws.com/03753020-4f11-4175-8523-330762c8abd9/3fbb07e1-b698-493c-9003-4eb43712b987/eaf216ff-c704-401d-8c71-36445d6f58fc.png?X-Amz-Algorithm=AWS4-HMAC-SHA256&X-Amz-Content-Sha256=UNSIGNED-PAYLOAD&X-Amz-Credential=ASIAZI2LB4665NUM2YWX%2F20251023%2Fus-west-2%2Fs3%2Faws4_request&X-Amz-Date=20251023T172616Z&X-Amz-Expires=3600&X-Amz-Security-Token=IQoJb3JpZ2luX2VjEJH%2F%2F%2F%2F%2F%2F%2F%2F%2F%2FwEaCXVzLXdlc3QtMiJHMEUCIFSiz3vK3jPEG9w9HdvrT3ScAUOpBNlh%2BNl8ArFr3CPiAiEA%2FCoMv%2B%2BTGP8IGnedQuCNeUAhxi6HOJ2qVxsqirtUWVMq%2FwMIShAAGgw2Mzc0MjMxODM4MDUiDCLyCpiaScaOej4RjSrcA9AZp9RlRfxFaUFYRzA9E5AzENbGFcD6nT6YfOje2EK4tH6p%2BuCSBAQAy9K5E%2BCYTlunnGso%2F%2FQ0HHWAStYuXxC9gZnfxMKdqu2ZrJuNMR%2FiGzsX0XJ5YwSLckFNWBjrNbBLKm9pcc%2B8eT%2FNchxeieML9BtJfCLyp0653ginw6BqtJLdQULZpptdR09hdDJfgfuJNS12YYdO0MoFzmhdug8ytcLCsAWUvch9UmQr6PeMIs1QLujvoi0XBCCJ5U2kn0SLz1P6gb3F8IqxcW7jxbmmbOEn3JKvv3ZuxFZEJpJQ1sX5OZNxbg8WXKvD%2Ft1MPJv3DwmlHkkUeFgqRNJ1lC6uBVRtUoBP8VVDC0sOMNI6c9hVmqLGNdL%2BdiXYpu7aE4Ui%2F3Fd0ZNbem6RRvh0l5Lpx%2BPvnI1%2BcrfiyEcCu2%2BisdNRc50KEb9OmCg63TCK8lL51bNWHk%2Bxjkvkq7UZ1Bm0oKRYwx%2BIo0AZcnDZzsiyunfeqm5y6hzdRkMVPgXb8suAfbstPuv5cROwwFHwgl5WGta1NzAfDJ5YI6ukq9LjV%2BUwqTMBtskO8BoJtdqFN1%2BGA2NGR1XWj3c2LTUZ9JPhSnSS%2BH4rIr29OF6RLxu2j2aatMI00KS81%2FQ6MIy%2F6ccGOqUBnYs1xy0PmbhqYqADqG4VPuo2Yj2OTETRtoULIKecNEe79765f42B%2BQPu5DgyKckTjRtk45G3ogcB7OkzyzLDpwaQGewL4MQeAeBErkO6cNpSk%2F050ztpGgb1ucDkjMsQj3aOifei0QS9cEDosf%2FBpMVZ7XOwZY3VXDNE6Gr1QUfZQ82y4ZHZqQAXZa2qSAm456pCdVyKwkkEkU6NOVbqzZ5fBBw2&X-Amz-Signature=d4ba85fff79021b1cd714a8330ec6e99efe8bb760dd07f5f11806c103271e563&X-Amz-SignedHeaders=host&x-amz-checksum-mode=ENABLED&x-id=GetObject",
                    "ExpiryTime": "2025-10-23T18:26:16.057Z"
                  }
                }
              },
              {
                "Id": "5e1e9caa-fe9a-496a-a77a-cfcc27b3f220",
                "Type": "image",
                "HasChildren": false,
                "Image": {
                  "Caption": [
                    {
                      "Annotation": {
                        "Bold": false,
                        "Italic": false,
                        "Strikethrough": false,
                        "Underline": false,
                        "Code": false,
                        "Color": "default"
                      },
                      "PlainText": "“Forest Conversion” von Johann Klause und Lucas Habermeyer",
                      "Href": null,
                      "Text": {
                        "Content": "“Forest Conversion” von Johann Klause und Lucas Habermeyer"
                      }
                    }
                  ],
                  "Type": "file",
                  "File": {
                    "Type": "file",
                    "Url": "https://prod-files-secure.s3.us-west-2.amazonaws.com/03753020-4f11-4175-8523-330762c8abd9/a2af4252-f254-4f59-a780-0068da28c303/lehrauftrag-tum_zukunftsvision.png?X-Amz-Algorithm=AWS4-HMAC-SHA256&X-Amz-Content-Sha256=UNSIGNED-PAYLOAD&X-Amz-Credential=ASIAZI2LB4665NUM2YWX%2F20251023%2Fus-west-2%2Fs3%2Faws4_request&X-Amz-Date=20251023T172616Z&X-Amz-Expires=3600&X-Amz-Security-Token=IQoJb3JpZ2luX2VjEJH%2F%2F%2F%2F%2F%2F%2F%2F%2F%2FwEaCXVzLXdlc3QtMiJHMEUCIFSiz3vK3jPEG9w9HdvrT3ScAUOpBNlh%2BNl8ArFr3CPiAiEA%2FCoMv%2B%2BTGP8IGnedQuCNeUAhxi6HOJ2qVxsqirtUWVMq%2FwMIShAAGgw2Mzc0MjMxODM4MDUiDCLyCpiaScaOej4RjSrcA9AZp9RlRfxFaUFYRzA9E5AzENbGFcD6nT6YfOje2EK4tH6p%2BuCSBAQAy9K5E%2BCYTlunnGso%2F%2FQ0HHWAStYuXxC9gZnfxMKdqu2ZrJuNMR%2FiGzsX0XJ5YwSLckFNWBjrNbBLKm9pcc%2B8eT%2FNchxeieML9BtJfCLyp0653ginw6BqtJLdQULZpptdR09hdDJfgfuJNS12YYdO0MoFzmhdug8ytcLCsAWUvch9UmQr6PeMIs1QLujvoi0XBCCJ5U2kn0SLz1P6gb3F8IqxcW7jxbmmbOEn3JKvv3ZuxFZEJpJQ1sX5OZNxbg8WXKvD%2Ft1MPJv3DwmlHkkUeFgqRNJ1lC6uBVRtUoBP8VVDC0sOMNI6c9hVmqLGNdL%2BdiXYpu7aE4Ui%2F3Fd0ZNbem6RRvh0l5Lpx%2BPvnI1%2BcrfiyEcCu2%2BisdNRc50KEb9OmCg63TCK8lL51bNWHk%2Bxjkvkq7UZ1Bm0oKRYwx%2BIo0AZcnDZzsiyunfeqm5y6hzdRkMVPgXb8suAfbstPuv5cROwwFHwgl5WGta1NzAfDJ5YI6ukq9LjV%2BUwqTMBtskO8BoJtdqFN1%2BGA2NGR1XWj3c2LTUZ9JPhSnSS%2BH4rIr29OF6RLxu2j2aatMI00KS81%2FQ6MIy%2F6ccGOqUBnYs1xy0PmbhqYqADqG4VPuo2Yj2OTETRtoULIKecNEe79765f42B%2BQPu5DgyKckTjRtk45G3ogcB7OkzyzLDpwaQGewL4MQeAeBErkO6cNpSk%2F050ztpGgb1ucDkjMsQj3aOifei0QS9cEDosf%2FBpMVZ7XOwZY3VXDNE6Gr1QUfZQ82y4ZHZqQAXZa2qSAm456pCdVyKwkkEkU6NOVbqzZ5fBBw2&X-Amz-Signature=ecd4fabd67720a59ad5db7c03010cdd410efd60145ec278683094088796334bd&X-Amz-SignedHeaders=host&x-amz-checksum-mode=ENABLED&x-id=GetObject",
                    "ExpiryTime": "2025-10-23T18:26:16.059Z"
                  }
                }
              }
            ]
          },
          {
            "Id": "fa4e4357-fde8-4e3e-8a01-b7276e9b147f",
            "Type": "column",
            "HasChildren": true,
            "Children": [
              {
                "Id": "fc653ef9-cd1a-476e-9648-5b69ed6a68a2",
                "Type": "image",
                "HasChildren": false,
                "Image": {
                  "Caption": [
                    {
                      "Annotation": {
                        "Bold": false,
                        "Italic": false,
                        "Strikethrough": false,
                        "Underline": false,
                        "Code": false,
                        "Color": "default"
                      },
                      "PlainText": "“Material Experiments” von Mara Starka und Johanna Wulff",
                      "Href": null,
                      "Text": {
                        "Content": "“Material Experiments” von Mara Starka und Johanna Wulff"
                      }
                    }
                  ],
                  "Type": "file",
                  "File": {
                    "Type": "file",
                    "Url": "https://prod-files-secure.s3.us-west-2.amazonaws.com/03753020-4f11-4175-8523-330762c8abd9/fd155e9c-a077-486e-a989-ec962fcf6caa/lehrauftrag-tum_material_experiments.png?X-Amz-Algorithm=AWS4-HMAC-SHA256&X-Amz-Content-Sha256=UNSIGNED-PAYLOAD&X-Amz-Credential=ASIAZI2LB46625F2OZXD%2F20251023%2Fus-west-2%2Fs3%2Faws4_request&X-Amz-Date=20251023T172616Z&X-Amz-Expires=3600&X-Amz-Security-Token=IQoJb3JpZ2luX2VjEJH%2F%2F%2F%2F%2F%2F%2F%2F%2F%2FwEaCXVzLXdlc3QtMiJGMEQCIHpPOKJUa8LO6%2BUXw0M4r8cQ4Lu4jCH3b3fR1yOKtQyvAiAD269ujJKRBDWtkSqEeGjN%2FFy08tw7zAKSnbni%2FpXYdir%2FAwhKEAAaDDYzNzQyMzE4MzgwNSIMNBZClmbo4P%2Fv5COPKtwDdOzPj62IZOyx9Jb%2FZ4FQyDmdkUS9ZVMDDbCw2GtK6eE94YB5U%2FlLei8xDXBd2H1KS3u3AYp2ea0NwAlaVP1G0%2FBDyOnsVMxjEcsfROHYamG%2Bt%2BuSQ%2BdgFdEuDaOy%2BN1KPb2ezyozRmM%2B%2FvRnUJmmQGA%2Bb8yJNyXNC%2BwNPWI31ZS%2BEswSUfsJLD9VC0qz7z99GDMrU480hF4rk1NvxdNwY83ZC5dRJIKdHS007SVGwdYIO3CUsNur2j4XaQZF1CQFQDUetDq980wyXrJxRiYumgaJ08o0gg5t89iNFoMhovDSKaue3TZgmABvgZhtGr68%2BtYW6kD98hWf9hj2x3EbMRXJdxXaVi76R9tzmrhb%2BkZ9rEH1VgNbg%2FTloIEMeZu7SN%2FZtDyzd2WpGK6VcViUtG218vLCfLm5yaLIygwbS2gQsnTOlBtNVbMXfsFMiy8pLjRmK0r%2FKReTtb2Jpfy9XX3pXCDIq7ubTuwj%2Babb3sUlYOdOoaIIS8%2FXj%2FXNnx%2FCW1A7Rh7RyZPY3xyC%2FxssCIVcUmuOaBD0%2Bn9%2B8BvmdTK%2FoR%2FDK%2BcXJOwJ6Jf4YeysxwdDBXvrsZabaN14gYtB16csJJWfAFTiTZHhx7nsSiLAdDSMQIDlju%2B0FBww4b7pxwY6pgEf%2BRKtlKpK%2F%2FjUGgYXLFAY97v52eG9K8WCWV2AVbsZ4OuoX0Kp775g9zf%2FMr6GhgaHieg2Zj%2BICzDGqYKvzW%2FI%2FAXRWBW%2BDgWkSVRG%2Btb6xv40XBRFgm7FalLcprsX5wA%2F7MSRraLQx91h03DHuowJLOCuYnWpIO3vffvZy6aQb73aFpSwZXTSZr2SQ68JR5VYFVAQPkof0WFDOYOuHyRLxovKZIjV&X-Amz-Signature=db5f7d436d72e44c80c915e65165343097f9e7ee2f7fbfc9b71d806936a7a72c&X-Amz-SignedHeaders=host&x-amz-checksum-mode=ENABLED&x-id=GetObject",
                    "ExpiryTime": "2025-10-23T18:26:16.071Z"
                  }
                }
              },
              {
                "Id": "401c74ca-972d-4b95-a6b2-61ea6aed6b31",
                "Type": "image",
                "HasChildren": false,
                "Image": {
                  "Caption": [
                    {
                      "Annotation": {
                        "Bold": false,
                        "Italic": false,
                        "Strikethrough": false,
                        "Underline": false,
                        "Code": false,
                        "Color": "default"
                      },
                      "PlainText": "Filmstill aus “HOLZWe.G.” von Max Malte Messner und Ben Klages",
                      "Href": null,
                      "Text": {
                        "Content": "Filmstill aus “HOLZWe.G.” von Max Malte Messner und Ben Klages"
                      }
                    }
                  ],
                  "Type": "file",
                  "File": {
                    "Type": "file",
                    "Url": "https://prod-files-secure.s3.us-west-2.amazonaws.com/03753020-4f11-4175-8523-330762c8abd9/35e52c8b-d4ad-43c4-ab51-b868795a229c/lehrauftrag-tum_film_still.png?X-Amz-Algorithm=AWS4-HMAC-SHA256&X-Amz-Content-Sha256=UNSIGNED-PAYLOAD&X-Amz-Credential=ASIAZI2LB46625F2OZXD%2F20251023%2Fus-west-2%2Fs3%2Faws4_request&X-Amz-Date=20251023T172616Z&X-Amz-Expires=3600&X-Amz-Security-Token=IQoJb3JpZ2luX2VjEJH%2F%2F%2F%2F%2F%2F%2F%2F%2F%2FwEaCXVzLXdlc3QtMiJGMEQCIHpPOKJUa8LO6%2BUXw0M4r8cQ4Lu4jCH3b3fR1yOKtQyvAiAD269ujJKRBDWtkSqEeGjN%2FFy08tw7zAKSnbni%2FpXYdir%2FAwhKEAAaDDYzNzQyMzE4MzgwNSIMNBZClmbo4P%2Fv5COPKtwDdOzPj62IZOyx9Jb%2FZ4FQyDmdkUS9ZVMDDbCw2GtK6eE94YB5U%2FlLei8xDXBd2H1KS3u3AYp2ea0NwAlaVP1G0%2FBDyOnsVMxjEcsfROHYamG%2Bt%2BuSQ%2BdgFdEuDaOy%2BN1KPb2ezyozRmM%2B%2FvRnUJmmQGA%2Bb8yJNyXNC%2BwNPWI31ZS%2BEswSUfsJLD9VC0qz7z99GDMrU480hF4rk1NvxdNwY83ZC5dRJIKdHS007SVGwdYIO3CUsNur2j4XaQZF1CQFQDUetDq980wyXrJxRiYumgaJ08o0gg5t89iNFoMhovDSKaue3TZgmABvgZhtGr68%2BtYW6kD98hWf9hj2x3EbMRXJdxXaVi76R9tzmrhb%2BkZ9rEH1VgNbg%2FTloIEMeZu7SN%2FZtDyzd2WpGK6VcViUtG218vLCfLm5yaLIygwbS2gQsnTOlBtNVbMXfsFMiy8pLjRmK0r%2FKReTtb2Jpfy9XX3pXCDIq7ubTuwj%2Babb3sUlYOdOoaIIS8%2FXj%2FXNnx%2FCW1A7Rh7RyZPY3xyC%2FxssCIVcUmuOaBD0%2Bn9%2B8BvmdTK%2FoR%2FDK%2BcXJOwJ6Jf4YeysxwdDBXvrsZabaN14gYtB16csJJWfAFTiTZHhx7nsSiLAdDSMQIDlju%2B0FBww4b7pxwY6pgEf%2BRKtlKpK%2F%2FjUGgYXLFAY97v52eG9K8WCWV2AVbsZ4OuoX0Kp775g9zf%2FMr6GhgaHieg2Zj%2BICzDGqYKvzW%2FI%2FAXRWBW%2BDgWkSVRG%2Btb6xv40XBRFgm7FalLcprsX5wA%2F7MSRraLQx91h03DHuowJLOCuYnWpIO3vffvZy6aQb73aFpSwZXTSZr2SQ68JR5VYFVAQPkof0WFDOYOuHyRLxovKZIjV&X-Amz-Signature=d7c77217941712cfc4d8d61a10c9d27630b6af27d82259f41424e957ce2c8f4f&X-Amz-SignedHeaders=host&x-amz-checksum-mode=ENABLED&x-id=GetObject",
                    "ExpiryTime": "2025-10-23T18:26:16.070Z"
                  }
                }
              }
            ]
          }
        ]
      }
    },
    {
      "Id": "16ce9761-9c0d-44ae-9bea-6b6882f13a26",
      "Type": "column_list",
      "HasChildren": true,
      "ParentId": "01a1e2d2-3f1f-4aae-b756-6e6bbde8bef3",
      "ColumnList": {
        "Columns": [
          {
            "Id": "2fa4e16b-4089-4cae-bf0f-3fca9c5d2930",
            "Type": "column",
            "HasChildren": true,
            "Children": [
              {
                "Id": "c8d3c9ed-3f46-4d4f-9e96-a9e014a23631",
                "Type": "image",
                "HasChildren": false,
                "Image": {
                  "Caption": [
                    {
                      "Annotation": {
                        "Bold": false,
                        "Italic": false,
                        "Strikethrough": false,
                        "Underline": false,
                        "Code": false,
                        "Color": "default"
                      },
                      "PlainText": "Übersicht der Ausstellung im Pavillon 333",
                      "Href": null,
                      "Text": {
                        "Content": "Übersicht der Ausstellung im Pavillon 333"
                      }
                    }
                  ],
                  "Type": "file",
                  "File": {
                    "Type": "file",
                    "Url": "https://prod-files-secure.s3.us-west-2.amazonaws.com/03753020-4f11-4175-8523-330762c8abd9/51eaf306-7988-4534-bb1f-b6bc5e3b331c/lehrauftrag-tum_concluding_event_2.png?X-Amz-Algorithm=AWS4-HMAC-SHA256&X-Amz-Content-Sha256=UNSIGNED-PAYLOAD&X-Amz-Credential=ASIAZI2LB466SX3RLRLR%2F20251023%2Fus-west-2%2Fs3%2Faws4_request&X-Amz-Date=20251023T172617Z&X-Amz-Expires=3600&X-Amz-Security-Token=IQoJb3JpZ2luX2VjEJH%2F%2F%2F%2F%2F%2F%2F%2F%2F%2FwEaCXVzLXdlc3QtMiJIMEYCIQCqk6W6ooa5VVxUAAqOvhAzmkh7zXVZRNZ3XnHWmYoT1wIhAPm6BoeeolaTD%2FAJUEjJyupVaM7BAeQutEBc1PswmOKXKv8DCEoQABoMNjM3NDIzMTgzODA1IgzCJlgX%2BWaTEpKKgBEq3APoGTKHkW5ndpORN9wWUt2g9ilvt3ct8jC6WZmKSapjSyHck6MGCKWLeM9DJObMqNDz%2F8qf4v5UZi2Xno8zIwc%2BemRlnXCD4zBTyxcGotdX58h54H6P6U3TaQXi37Jh0XL0dsO464LwQruoU79NR2gLxUTYICEbAtSORg2zqoN2kGtVXSSjEAe6QoPEP%2BGjlx2fHYLRYk9tZ3rR%2Bhw%2FQe5d6iZBHWe71E%2FOMRwWGuyDP9F7wpdGytBopWHyfrI6D8atkxest6OaY44%2Fq8cXMqSFvuvM0wSHKcQPGrk5Fx%2Fr97h8vKoTTephsYdC%2FSz%2BSf3DUC3T5LkLX5PEOu2JbiJCUsennvuqY3s7Z%2F28Hg7mzvCHZbmXS2Wp9SaS3J0wN3cXRR%2BA%2FHgRVYg5nbl0v4YncCvehddcwtpJy5bVVkY%2BxZ8UvCPhBDiM0RHCG6ky5YckLU1I%2BVxQXPJfXKv0eLburTA8GeVqL9Dy8DNjCRgYUE1Tlxc2My9HG2QRfn6HAmKZeunSZRsdDaq8HXi14k8JPwjFy%2BivpNNoq8UURmigqJPog%2FHBFYIKF5wbMXVqc1X834R6vlQputTPego9FJh7GWw9JFsRxkkt3qn2TZefuIThGZl9%2Fy7baw80azDKvunHBjqkARrkpKX%2BEaEmSjby%2BBT2CxRRzr%2ByjDWlzfCXKNt9lPopGH9h5An8Qh6qk7TFzIp1oMpNAn49qi0Wdo34gYd9IQhf7G3PtF80jAkR%2Fu%2BvNDTsPqkN%2BhfAee9ebM6lwilSva3rtC38XC7rLG68oQUDahG96m0hkNAoeR%2F95hHTKnAQNJPI0uNSRK%2Bk%2FyKMHKst%2Fc58Yuy3LbyihLGxtN3Muw43xZpQ&X-Amz-Signature=e6c8d0d391be3c659b424a6ceb42d139a032ec0bf9f5b56b43db92870a7d328e&X-Amz-SignedHeaders=host&x-amz-checksum-mode=ENABLED&x-id=GetObject",
                    "ExpiryTime": "2025-10-23T18:26:17.603Z"
                  }
                }
              },
              {
                "Id": "66772345-e314-453c-8f4e-d5382e598ac0",
                "Type": "paragraph",
                "HasChildren": false,
                "Paragraph": {
                  "RichTexts": [],
                  "Color": "default"
                }
              }
            ]
          },
          {
            "Id": "9ffc409b-039e-48d7-9052-27b9deae2939",
            "Type": "column",
            "HasChildren": true,
            "Children": [
              {
                "Id": "fc3d054e-850b-49b4-8ae5-a50fd5d8e8ea",
                "Type": "image",
                "HasChildren": false,
                "Image": {
                  "Caption": [
                    {
                      "Annotation": {
                        "Bold": false,
                        "Italic": false,
                        "Strikethrough": false,
                        "Underline": false,
                        "Code": false,
                        "Color": "default"
                      },
                      "PlainText": "Ausstellung im Pavillon 333",
                      "Href": null,
                      "Text": {
                        "Content": "Ausstellung im Pavillon 333"
                      }
                    }
                  ],
                  "Type": "file",
                  "File": {
                    "Type": "file",
                    "Url": "https://prod-files-secure.s3.us-west-2.amazonaws.com/03753020-4f11-4175-8523-330762c8abd9/6c6839c0-19e4-414e-9209-7739dfe46b1c/lehrauftrag-tum_concluding_event_3.png?X-Amz-Algorithm=AWS4-HMAC-SHA256&X-Amz-Content-Sha256=UNSIGNED-PAYLOAD&X-Amz-Credential=ASIAZI2LB4663T5JEGK3%2F20251023%2Fus-west-2%2Fs3%2Faws4_request&X-Amz-Date=20251023T172617Z&X-Amz-Expires=3600&X-Amz-Security-Token=IQoJb3JpZ2luX2VjEJH%2F%2F%2F%2F%2F%2F%2F%2F%2F%2FwEaCXVzLXdlc3QtMiJHMEUCIQCjOm%2FRLmXWhxgoKrzVgbrPfjVTVn6kI%2BQt6FRA4mdp8wIgX5IhNf7m3l8ktGqNXcIWCJmmJCNwBkzkhdBSqwOCHJQq%2FwMIShAAGgw2Mzc0MjMxODM4MDUiDBKySnInFloTL2vAFyrcA8Om1yTCo1312yy%2FVb%2FmpzCewr%2BjuSl0qK%2F9etGrjU5qym%2F2GWRA1en9OUeg1GZdGPUppyWsQ91AguiuLPHSxYXEVWFzeGd31NNyQkqGXYGAzcpE%2FAoV8SQ632RlfUAlD4r7vwpBxKlEKYmcTSzg8gEo2ahk3MZjAOgizmj0tKAHtmj0ayQXykP59lVGssnvhRPLbstxqwbKKYAu9BQq4TOQfHZSxZ6s3tcWyttFcx5s7ko82D51Z9psxuL1rSZsZxx54yyxpVhWshK4lQRjeuXvaJcLfJ8MGBeFkC8FSFDZHgkyiT6qYSnat6YHtBFHSst3j2txQxY%2FnzJ8AZMprgCp5kJvsqmLYbVGGf9Kl6gay7dUGArsZNSKwkd%2FnVNo67RrYpNX4y%2FTMPmY1YaxpgeulVJI3IMej3%2BOQ0dSlVKQ3rHyNd0GKYlywTqEgr%2FTR6YNTSXLrG1CE4Wt%2F2G65FjiLObDCsz2C5LNjD6vkFvvyd2U0cJmXmALDQ%2BzfYIHqZKbDUkHEdT%2Bt%2F6bvV0CdEU2hEs6k5T679UHm84lPJO9lUdDIWdxLuMJCKgpKGb3G2kJpGnvAi3oP7taLaNem8dcD6MH2t7BiAEWeDra%2BCrxsa2MQtdNFY1SdgnAMIO%2F6ccGOqUBcbu51oDIimKNUoAv9y5MBFOeghfImOZ8ZiwYLc4NWsKSMve2rWvg2MKLgNN%2FKtYbDDXb5EOuWMg7%2F%2FIYh8s1fTBoEe3fwKYTtd6EusbCKkgLMRi1JdnDEfaVKqfNs1PTk55gcK%2Ft7lEZHwLWSrDvd6i%2FtgMUA3OFfKmNgxJwNIOBKCNrh%2FJtgh3sgez7kFjIAujewA9CklL93wW%2BSMM5Fscyvnzq&X-Amz-Signature=201fc285b3e71edbded175b79734686941ea744813323346c2a47b74b18704d8&X-Amz-SignedHeaders=host&x-amz-checksum-mode=ENABLED&x-id=GetObject",
                    "ExpiryTime": "2025-10-23T18:26:17.961Z"
                  }
                }
              },
              {
                "Id": "9ce57be5-4e57-419b-847c-c7a54ace2611",
                "Type": "paragraph",
                "HasChildren": false,
                "Paragraph": {
                  "RichTexts": [],
                  "Color": "default"
                }
              }
            ]
          }
        ]
      }
    },
    {
      "Id": "5a382f3d-ed9c-4fd9-9901-e0017cc553f8",
      "Type": "paragraph",
      "HasChildren": false,
      "ParentId": "01a1e2d2-3f1f-4aae-b756-6e6bbde8bef3",
      "Paragraph": {
        "RichTexts": [
          {
            "Annotation": {
              "Bold": false,
              "Italic": false,
              "Strikethrough": false,
              "Underline": false,
              "Code": false,
              "Color": "default"
            },
            "PlainText": "©️ ",
            "Href": null,
            "Text": {
              "Content": "©️ "
            }
          },
          {
            "Annotation": {
              "Bold": false,
              "Italic": false,
              "Strikethrough": false,
              "Underline": false,
              "Code": false,
              "Color": "default"
            },
            "PlainText": "Cover & Images: Max Malte Messner",
            "Href": null,
            "Text": {
              "Content": "Cover & Images: Max Malte Messner"
            }
          }
        ],
        "Color": "default"
      }
    },
    {
      "Id": "8fada4da-930a-4319-8a41-1cb0873f8a37",
      "Type": "paragraph",
      "HasChildren": false,
      "ParentId": "01a1e2d2-3f1f-4aae-b756-6e6bbde8bef3",
      "Paragraph": {
        "RichTexts": [
          {
            "Annotation": {
              "Bold": false,
              "Italic": false,
              "Strikethrough": false,
              "Underline": false,
              "Code": false,
              "Color": "default"
            },
            "PlainText": "Cover: How to Circulate, Zeynep Argat und Patricija Helena Dzerve",
            "Href": null,
            "Text": {
              "Content": "Cover: How to Circulate, Zeynep Argat und Patricija Helena Dzerve"
            }
          }
        ],
        "Color": "default"
      }
    },
    {
      "Id": "beab31e3-1ec4-4d29-bcbb-9e25111d0bcb",
      "Type": "paragraph",
      "HasChildren": false,
      "ParentId": "01a1e2d2-3f1f-4aae-b756-6e6bbde8bef3",
      "Paragraph": {
        "RichTexts": [],
        "Color": "default"
      }
    }
  ]
}